{"status":"done","publicPath":"http://localhost:3000/frontend/bundles/","chunks":{"main":[{"name":"main-d1a5f6798c9ccefa248b.js","publicPath":"http://localhost:3000/frontend/bundles/main-d1a5f6798c9ccefa248b.js","path":"/Users/spencerchristensen/Projects/frasier/frontend/bundles/main-d1a5f6798c9ccefa248b.js"},{"name":"main.6ea7824b2b9a2f6199b7.hot-update.js","publicPath":"http://localhost:3000/frontend/bundles/main.6ea7824b2b9a2f6199b7.hot-update.js","path":"/Users/spencerchristensen/Projects/frasier/frontend/bundles/main.6ea7824b2b9a2f6199b7.hot-update.js"}]},"error":"ModuleBuildError","message":"Module build failed: SyntaxError: Unexpected token (28:6)\n\n  26 |         </ul>\n  27 |         <button onClick={addNewPlayer}\n> 28 |       </div>\n     |       ^\n  29 |     );\n  30 |   }\n  31 | }\n"}